Metadata-Version: 1.0
Name: distributionsbi
Version: 0.1
Summary: Gaussian and binomial distributions
Home-page: UNKNOWN
Author: Pratik Patil
Author-email: pratikmpatil12@gmail.com
License: UNKNOWN
Platform: UNKNOWN
